outline_typst/__init__.py
outline_typst/converter.py
outline_typst-0.1.0.dist-info/licenses/LICENSE
outline_typst-0.1.0.dist-info/METADATA
outline_typst-0.1.0.dist-info/WHEEL
outline_typst-0.1.0.dist-info/top_level.txt
outline_typst-0.1.0.dist-info/RECORD
