Metadata-Version: 2.4
Name: outline-typst
Version: 0.1.0
Summary: Convert Outline exports to Typst markup
Author-email: Lamkateh <perruque-gruau-7k@icloud.com>
License-Expression: MIT
Project-URL: Homepage, https://github.com/Lamkateh/outline-typst
Project-URL: Issues, https://github.com/Lamkateh/outline-typst/issues
Requires-Python: >=3.10
License-File: LICENSE
Requires-Dist: pytest>=8.4.2
Requires-Dist: requests>=2.32.5
Dynamic: license-file
